LICENSE.txt
MANIFEST.in
README.md
pyproject.toml
setup.cfg
setup.py
src/WaveGenPy/InSquareFourier.py
src/WaveGenPy/InToneFunc.py
src/WaveGenPy/OutWaveFunc.py
src/WaveGenPy/WaveGenEngine.py
src/WaveGenPy/WavePara.py
src/WaveGenPy/__init__.py
src/WaveGenPy.egg-info/PKG-INFO
src/WaveGenPy.egg-info/SOURCES.txt
src/WaveGenPy.egg-info/dependency_links.txt
src/WaveGenPy.egg-info/top_level.txt
src/WaveGenPy/Sample/SampleSquareFourier.py
src/WaveGenPy/Sample/SampleTone.py
src/WaveGenPy/Sample/__init__.py