Metadata-Version: 2.1
Name: WaveGenPy
Version: 0.1.0
Summary: Wave file generator
Home-page: https://github.com/EfiPy/WaveGenPy
Author: MaxWu
Author-email: EfiPy.Core@gmail.com
License: UNKNOWN
Platform: UNKNOWN
Classifier: License :: Other/Proprietary License
Classifier: Development Status :: 3 - Alpha
Classifier: Operating System :: POSIX
Classifier: Programming Language :: Python :: 3
Classifier: Programming Language :: Python :: 3.6
Classifier: Programming Language :: Python :: 3.7
Classifier: Programming Language :: Python :: 3.8
Classifier: Programming Language :: Python :: 3.9
Classifier: Programming Language :: Python :: 3 :: Only
Classifier: Topic :: Software Development :: Libraries
Classifier: Topic :: Software Development :: Testing :: Unit
Classifier: Topic :: Multimedia :: Sound/Audio :: Sound Synthesis
Classifier: Topic :: Scientific/Engineering :: Mathematics
Requires-Python: >=3.5, <4
